bl3_cli_saveedit-1.18.0.data/data/share/bl3-cli-saveedit/COPYING.txt
bl3_cli_saveedit-1.18.0.data/data/share/bl3-cli-saveedit/README-profile.md
bl3_cli_saveedit-1.18.0.data/data/share/bl3-cli-saveedit/README-saves.md
bl3_cli_saveedit-1.18.0.data/data/share/bl3-cli-saveedit/README.md
bl3_cli_saveedit-1.18.0.data/data/share/bl3-cli-saveedit/item_exports/mod_testing_gear.txt
bl3_cli_saveedit-1.18.0.data/data/share/bl3-cli-saveedit/protobufs/OakProfile.proto
bl3_cli_saveedit-1.18.0.data/data/share/bl3-cli-saveedit/protobufs/OakSave.proto
bl3_cli_saveedit-1.18.0.data/data/share/bl3-cli-saveedit/protobufs/OakShared.proto
bl3_cli_saveedit-1.18.0.data/data/share/bl3-cli-saveedit/protobufs/README.md
bl3save/OakProfile_pb2.py
bl3save/OakSave_pb2.py
bl3save/OakShared_pb2.py
bl3save/__init__.py
bl3save/bl3profile.py
bl3save/bl3save.py
bl3save/cli_archive.py
bl3save/cli_common.py
bl3save/cli_copy_pt.py
bl3save/cli_edit.py
bl3save/cli_import_json.py
bl3save/cli_import_protobuf.py
bl3save/cli_info.py
bl3save/cli_prof_edit.py
bl3save/cli_prof_import_json.py
bl3save/cli_prof_import_protobuf.py
bl3save/cli_prof_info.py
bl3save/datalib.py
bl3save/resources/balance_name_mapping.json.xz
bl3save/resources/balance_to_inv_key.json.xz
bl3save/resources/inventoryserialdb.json.xz
bl3save/resources/short_name_balance_mapping.json.xz
bl3_cli_saveedit-1.18.0.dist-info/COPYING.txt
bl3_cli_saveedit-1.18.0.dist-info/METADATA
bl3_cli_saveedit-1.18.0.dist-info/WHEEL
bl3_cli_saveedit-1.18.0.dist-info/entry_points.txt
bl3_cli_saveedit-1.18.0.dist-info/top_level.txt
bl3_cli_saveedit-1.18.0.dist-info/RECORD
