Metadata-Version: 2.1
Name: bl3-cli-saveedit
Version: 1.18.0
Summary: Borderlands 3 Savegame Editor
Home-page: https://github.com/apocalyptech/bl3-cli-saveedit
Author: CJ Kucera
Author-email: cj@apocalyptech.com
License: zlib/libpng
Classifier: Development Status :: 5 - Production/Stable
Classifier: Environment :: Console
Classifier: Intended Audience :: End Users/Desktop
Classifier: License :: OSI Approved :: zlib/libpng License
Classifier: Natural Language :: English
Classifier: Operating System :: OS Independent
Classifier: Programming Language :: Python :: 3
Classifier: Topic :: Games/Entertainment :: First Person Shooters
Classifier: Topic :: Utilities
Requires-Python: >=3.9
License-File: COPYING.txt
Requires-Dist: protobuf >=3.12,~=3.0
